[
  {
    "key": "restorative.tea.slow.v1",
    "category": "restorative",
    "minutes": 6,
    "activity": "Make a cup of tea or coffee and drink it slowly",
    "done_condition": "when the mug is empty",
    "location": "any",
    "rarity": "common",
    "tags": ["low_energy", "reset", "sensory"],
    "active": true
  },
  {
    "key": "restorative.water.refill.v1",
    "category": "restorative",
    "minutes": 3,
    "activity": "Refill your water and take 10 slow sips",
    "done_condition": "after the 10th sip",
    "location": "any",
    "rarity": "common",
    "tags": ["low_energy", "reset"],
    "active": true
  },
  {
    "key": "restorative.breath.box4.v1",
    "category": "restorative",
    "minutes": 4,
    "activity": "Box breathing: 4 in, hold 4, out 4, hold 4",
    "done_condition": "after 4 minutes on a timer",
    "location": "any",
    "rarity": "common",
    "tags": ["anxious", "reset"],
    "active": true
  },
  {
    "key": "restorative.eyes.offscreen.v1",
    "category": "restorative",
    "minutes": 2,
    "activity": "Stand up and look out a window (eyes off screens)",
    "done_condition": "after 2 minutes on a timer",
    "location": "indoor",
    "rarity": "common",
    "tags": ["low_energy", "eyes"],
    "active": true
  },
  {
    "key": "physical.mobility.neck_shoulders.v1",
    "category": "physical",
    "minutes": 5,
    "activity": "5-minute mobility: neck rolls, shoulder circles, hip hinges",
    "done_condition": "after 5 minutes on a timer",
    "location": "any",
    "rarity": "common",
    "tags": ["restless", "reset"],
    "active": true
  },
  {
    "key": "physical.squats.30.v1",
    "category": "physical",
    "minutes": 3,
    "activity": "Do 30 slow bodyweight squats",
    "done_condition": "when you finish rep 30",
    "location": "home",
    "rarity": "common",
    "tags": ["restless", "energy"],
    "active": true
  },
  {
    "key": "physical.pushups.20.v1",
    "category": "physical",
    "minutes": 3,
    "activity": "Do 20 pushups (modify as needed)",
    "done_condition": "when you complete 20 total reps",
    "location": "home",
    "rarity": "common",
    "tags": ["restless", "energy"],
    "active": true
  },
  {
    "key": "physical.plank.90s.v1",
    "category": "physical",
    "minutes": 2,
    "activity": "Hold a plank (or side plank) for 90 seconds",
    "done_condition": "when the timer hits 90 seconds",
    "location": "home",
    "rarity": "uncommon",
    "tags": ["restless", "focus"],
    "active": true
  },
  {
    "key": "creative.ugly_sentences.5.v1",
    "category": "creative",
    "minutes": 6,
    "activity": "Write 5 ugly sentences about what you’re working on",
    "done_condition": "when you have 5 sentences (even bad ones)",
    "location": "indoor",
    "rarity": "common",
    "tags": ["avoidance", "momentum"],
    "active": true
  },
  {
    "key": "creative.sketch.3boxes.v1",
    "category": "creative",
    "minutes": 7,
    "activity": "Sketch the problem with 3 labeled boxes and arrows",
    "done_condition": "when the 3 boxes are labeled",
    "location": "indoor",
    "rarity": "uncommon",
    "tags": ["clarity", "avoidance"],
    "active": true
  },
  {
    "key": "creative.voice_memo.2min.v1",
    "category": "creative",
    "minutes": 3,
    "activity": "Record a 2-minute voice memo: what’s stuck + next step",
    "done_condition": "when the memo is saved",
    "location": "any",
    "rarity": "uncommon",
    "tags": ["clarity", "avoidance"],
    "active": true
  },
  {
    "key": "intellectual.one_page_book.v1",
    "category": "intellectual",
    "minutes": 7,
    "activity": "Read one page of a book you’ve been meaning to read",
    "done_condition": "after you finish 1 page",
    "location": "any",
    "rarity": "common",
    "tags": ["low_energy", "reset"],
    "active": true
  },
  {
    "key": "intellectual.3bullets.believe_need_next.v1",
    "category": "intellectual",
    "minutes": 5,
    "activity": "Write 3 bullets: what I believe / what I need to know / what’s next",
    "done_condition": "when you have 3 bullets",
    "location": "indoor",
    "rarity": "common",
    "tags": ["anxious", "clarity"],
    "active": true
  },
  {
    "key": "social.checkin.text.v1",
    "category": "social",
    "minutes": 4,
    "activity": "Send one quick check-in text to a friend",
    "done_condition": "when the message is sent",
    "location": "any",
    "rarity": "common",
    "tags": ["connection", "reset"],
    "active": true
  },
  {
    "key": "social.voice_message.60s.v1",
    "category": "social",
    "minutes": 3,
    "activity": "Send a 60-second voice message to someone you like",
    "done_condition": "when it’s sent",
    "location": "any",
    "rarity": "uncommon",
    "tags": ["connection", "reset"],
    "active": true
  },
  {
    "key": "work_momentum.3todos.v1",
    "category": "work_momentum",
    "minutes": 6,
    "activity": "Open the thing you’re avoiding and write 3 tiny TODOs",
    "done_condition": "when you have 3 TODO items",
    "location": "indoor",
    "rarity": "common",
    "tags": ["avoidance", "momentum"],
    "active": true
  },
  {
    "key": "work_momentum.5min.timer.v1",
    "category": "work_momentum",
    "minutes": 5,
    "activity": "Do the smallest next action for 5 minutes (timer on)",
    "done_condition": "when the timer ends",
    "location": "indoor",
    "rarity": "common",
    "tags": ["momentum", "focus"],
    "active": true
  },
  {
    "key": "work_momentum.ship_tiny.v1",
    "category": "work_momentum",
    "minutes": 8,
    "activity": "Ship one tiny thing: fix a typo, close an issue, send the email",
    "done_condition": "when it’s shipped/sent",
    "location": "indoor",
    "rarity": "uncommon",
    "tags": ["momentum", "closure"],
    "active": true
  },
  {
    "key": "outdoor.sun.3min.v1",
    "category": "restorative",
    "minutes": 3,
    "activity": "Stand in the sun for 3 minutes with eyes closed",
    "done_condition": "when the timer hits 3 minutes",
    "location": "outdoor",
    "rarity": "common",
    "tags": ["reset", "sensory"],
    "active": true
  },
  {
    "key": "outdoor.walk.block_loop.v1",
    "category": "physical",
    "minutes": 8,
    "activity": "Walk one block loop and return (no phone)",
    "done_condition": "when you’re back at your door",
    "location": "outdoor",
    "rarity": "common",
    "tags": ["restless", "reset"],
    "active": true
  },
  {
    "key": "ruzafa.mercado.buy_fruit.v1",
    "category": "physical",
    "minutes": 10,
    "activity": "Walk to Mercado de Ruzafa and buy one piece of fruit",
    "done_condition": "when you’re back with the fruit",
    "location": "ruzafa",
    "rarity": "rare",
    "tags": ["outdoor", "errand", "reset"],
    "active": true
  },
  {
    "key": "ruzafa.plaza.doctor_landete.3min.v1",
    "category": "restorative",
    "minutes": 7,
    "activity": "Sit in Plaza del Doctor Landete and notice 5 new things",
    "done_condition": "when you’ve noticed 5 things",
    "location": "ruzafa",
    "rarity": "rare",
    "tags": ["outdoor", "sensory", "reset"],
    "active": true
  },
  {
    "key": "valencia.estacion_norte.tiles.v1",
    "category": "creative",
    "minutes": 10,
    "activity": "Walk to Estación del Norte and admire the tilework",
    "done_condition": "when you’ve looked for 3 minutes then head back",
    "location": "valencia",
    "rarity": "rare",
    "tags": ["outdoor", "aesthetic", "reset"],
    "active": true
  },
  {
    "key": "valencia.plaza_ayuntamiento.bench.v1",
    "category": "restorative",
    "minutes": 10,
    "activity": "Walk to Plaza del Ayuntamiento, sit for 2 minutes, return",
    "done_condition": "when you’re back at your starting point",
    "location": "valencia",
    "rarity": "rare",
    "tags": ["outdoor", "reset"],
    "active": true
  }
]
